<?xml version="1.0"?>
<config>
  <draw_priority value="10"></draw_priority>
  <type value="1"></type>
  <frequency value="1000"></frequency>
  <max_emissions value="20"></max_emissions>
  <angle value="90" variation="25"></angle>
  <vel_mag value="0.5" variation="2.0"></vel_mag>
  <pos_var x="0" y="0"></pos_var>
  <lifetime value = "20" variation="5"></lifetime>
  <initial_scale value="2.0f" variation="0.3f"></initial_scale>
  <final_scale value="0.3f" variation="0"></final_scale>
  <initial_color r="200" g="0" b="0"></initial_color>
  <final_color r="70" g="0" b="0" a ="255"></final_color>
  <blend_mode value="1"></blend_mode>
  <texture_path value="particles/pixel.png"></texture_path>
</config>
